pygame_markdown/PygameMarkdown.py
pygame_markdown/__init__.py
pygame_markdown/_customization.py
pygame_markdown/_draw_code_background.py
pygame_markdown/_draw_lines.py
pygame_markdown/_draw_quote.py
pygame_markdown/_get_surface.py
pygame_markdown/_inline_preparations.py
pygame_markdown/_mouse.py
pygame_markdown/_render.py
pygame_markdown/_render_code.py
pygame_markdown/_render_list.py
pygame_markdown/_render_text.py
pygame_markdown/_scrollbar.py
pygame_markdown/_visibility.py
pygame_markdown-1.1.6.dist-info/LICENSE
pygame_markdown-1.1.6.dist-info/METADATA
pygame_markdown-1.1.6.dist-info/WHEEL
pygame_markdown-1.1.6.dist-info/top_level.txt
pygame_markdown-1.1.6.dist-info/RECORD
