Metadata-Version: 2.1
Name: pygame-markdown
Version: 1.1.6
Summary: A renderer for markdown text onto pygame surfaces.
Home-page: https://github.com/CribberSix/pygame-markdown
Author: CribberSix
Author-email: cribbersix@gmail.com
License: MIT
Keywords: pygame,markdown,text,rendering
Classifier: Development Status :: 5 - Production/Stable
Classifier: License :: OSI Approved :: MIT License
Classifier: Programming Language :: Python :: 3
Classifier: Programming Language :: Python :: 3.6
Classifier: Topic :: Software Development :: Libraries
Classifier: Topic :: Software Development :: Libraries :: Python Modules
Classifier: Intended Audience :: Developers
Classifier: Natural Language :: English
Classifier: Topic :: Software Development
Requires-Python: >=3.6
License-File: LICENSE
